xplus31/README.md
xplus31/__init__.py
xplus31/calcfun.py
xplus31/help.py
xplus31/immediate_test.py
xplus31/output/__init__.py
xplus31/src/__init__.py
xplus31/src/file5.py
xplus31/src/file7.py
xplus31/src/merge/__init__.py
xplus31/src/merge/file13.py
xplus31/src/merge/hint.py
xplus31/src/merge/deeper/__dumb.py
xplus31/src/merge/deeper/__init__.py
xplus31/src/merge/deeper/file31.py
xplus31/src/minus/__init__.py
xplus31/src/minus/file_1.py
xplus31-1.0.1.dist-info/METADATA
xplus31-1.0.1.dist-info/WHEEL
xplus31-1.0.1.dist-info/entry_points.txt
xplus31-1.0.1.dist-info/top_level.txt
xplus31-1.0.1.dist-info/RECORD
