Metadata-Version: 2.1
Name: xplus31
Version: 1.0.1
Summary: A simple test of package distribution with simple functions in it
Home-page: https://pypi.org/project/xplus31
Author: A.T.P.test
Author-email: nonsense@fake.email
Classifier: Development Status :: 3 - Alpha
Classifier: Programming Language :: Python :: 3
Classifier: Intended Audience :: Education
Classifier: License :: Freeware
Classifier: Operating System :: Microsoft :: Windows
Requires-Dist: numpy<2,>=1
